setup.cfg
setup.py
giftrocket/__init__.py
giftrocket/client.py
giftrocket/http.py
giftrocket/version.py
giftrocket_python.egg-info/PKG-INFO
giftrocket_python.egg-info/SOURCES.txt
giftrocket_python.egg-info/dependency_links.txt
giftrocket_python.egg-info/not-zip-safe
giftrocket_python.egg-info/requires.txt
giftrocket_python.egg-info/top_level.txt