Metadata-Version: 1.1
Name: giftrocket-python
Version: 2.0.0
Summary: Python API client for GiftRocket
Home-page: https://github.com/giftrocket/giftrocket-python
Author: Ben Rocket
Author-email: ben@giftrocket.com
License: MIT
Download-URL: https://github.com/giftrocket/giftrocket-python/tarball/v2.0.0
Keywords: api,gift cards,rewards,incentives,giftrocket
Platform: UNKNOWN
Classifier: Programming Language :: Python
Classifier: Programming Language :: Python :: 2
Classifier: Programming Language :: Python :: 2.7
Classifier: Programming Language :: Python :: 3
Classifier: Programming Language :: Python :: 3.4
Classifier: Topic :: Software Development :: Libraries :: Python Modules
Classifier: Environment :: Web Environment
